image432/ImageObject.py
image432/__init__.py
image432-0.0.1.dist-info/LICENSE
image432-0.0.1.dist-info/METADATA
image432-0.0.1.dist-info/WHEEL
image432-0.0.1.dist-info/top_level.txt
image432-0.0.1.dist-info/RECORD
