Metadata-Version: 2.1
Name: image432
Version: 0.0.1
Summary: A simple image package to demonstrate project development
Author: Will Heuer
Author-email: Abe Stroschein <ajstros@duck.com>
Classifier: Programming Language :: Python :: 3
Classifier: Operating System :: OS Independent
Requires-Python: >=3.7
License-File: LICENSE
